Workbook

Sheet DATA_DICTIONARY
A1: Column Name | B1: Description | C1: Notes
A2: Transaction_ID | B2: Unique identifier for each transaction (T001–T200) | C2: Primary key
A3: Date | B3: Date of transaction in DD/MM/YYYY format | C3: 2024 only
A4: Customer_ID | B4: Links to CUSTOMER_PROFILES sheet (CUST001–CUST030) | C4: Foreign key
A5: Transaction_Type | B5: Type: Salary Credit, Cash Deposit, Wire Transfer, Bill Payment etc | C5: Categorisation
A6: Amount_GBP | B6: Transaction amount in British Pounds Sterling | C6: Always positive
A7: Currency | B7: Transaction currency — GBP for domestic, others for international | C7: ISO code
A8: Counterparty_Name | B8: Name of the other party in the transaction | C8: For TM rules
A9: Counterparty_Country | B9: Country of the counterparty | C9: Used in Rule 3 FATF check
A10: Counterparty_Bank | B10: Bank used by the counterparty | C10: For investigation
A11: Direction | B11: Credit = money in, Debit = money out | C11: Always Credit or Debit
A12: Running_Balance | B12: Customer account balance after transaction | C12: Running total
... A15: Alert_ID | B15: Alert reference number — links to ALERT_INVESTIGATION_LOG | C15: ALT001–ALT010

Sheet CUSTOMER_PROFILES
A1: Customer_ID | B1: Customer_Type | C1: Nationality | D1: Country_of_Residence | E1: Occupation | F1: Risk_Rating | G1: KYC_Tier | H1: Monthly_Expected_Turnover_GBP | I1: Account_Status | J1: Account_Open_Date
A2: CUST001 | B2: Individual | C2: British | D2: UK | E2: Teacher | F2: Low | G2: =INDEX(KYC_CDD_FRAMEWORK!$K$30:$K$59,MATCH(A2,KYC_CDD_FRAMEWORK!$A$30:$A$59,0)) -> SDD | H2: 3500 | I2: Active | J2: 43466
A3: CUST002 | B3: Individual | C3: British | D3: UK | E3: Nurse | F3: Low | G3: =INDEX(KYC_CDD_FRAMEWORK!$K$30:$K$59,MATCH(A3,KYC_CDD_FRAMEWORK!$A$30:$A$59,0)) -> SDD | H3: 3200 | I3: Active | J3: 43174
A4: CUST003 | B4: Individual | C4: British | D4: UK | E4: Engineer | F4: Low | G4: =INDEX(KYC_CDD_FRAMEWORK!$K$30:$K$59,MATCH(A4,KYC_CDD_FRAMEWORK!$A$30:$A$59,0)) -> SDD | H4: 5500 | I4: Active | J4: 42906
A5: CUST004 | B5: Individual | C5: British | D5: UK | E5: Accountant | F5: Low | G5: =INDEX(KYC_CDD_FRAMEWORK!$K$30:$K$59,MATCH(A5,KYC_CDD_FRAMEWORK!$A$30:$A$59,0)) -> SDD | H5: 6000 | I5: Active | J5: 43840
A6: CUST005 | B6: Individual | C6: British | D6: UK | E6: Police Officer | F6: Low | G6: =INDEX(KYC_CDD_FRAMEWORK!$K$30:$K$59,MATCH(A6,KYC_CDD_FRAMEWORK!$A$30:$A$59,0)) -> SDD | H6: 3800 | I6: Active | J6: 43651
A7: CUST006 | B7: Individual | C7: British | D7: UK | E7: Retail Manager | F7: Low | G7: =INDEX(KYC_CDD_FRAMEWORK!$K$30:$K$59,MATCH(A7,KYC_CDD_FRAMEWORK!$A$30:$A$59,0)) -> SDD | H7: 3000 | I7: Active | J7: 43365
A8: CUST007 | B8: Individual | C8: British | D8: UK | E8: IT Analyst | F8: Low | G8: =INDEX(KYC_CDD_FRAMEWORK!$K$30:$K$59,MATCH(A8,KYC_CDD_FRAMEWORK!$A$30:$A$59,0)) -> CDD | H8: 4500 | I8: Active | J8: 43875
A9: CUST008 | B9: Individual | C9: British | D9: UK | E9: Social Worker | F9: Low | G9: =INDEX(KYC_CDD_FRAMEWORK!$K$30:$K$59,MATCH(A9,KYC_CDD_FRAMEWORK!$A$30:$A$59,0)) -> SDD | H9: 3300 | I9: Active | J9: 43069
A10: CUST009 | B10: Individual | C10: British | D10: UK | E10: Pharmacist | F10: Low | G10: =INDEX(KYC_CDD_FRAMEWORK!$K$30:$K$59,MATCH(A10,KYC_CDD_FRAMEWORK!$A$30:$A$59,0)) -> SDD | H10: 5000 | I10: Active | J10: 43563
A11: CUST010 | B11: Individual | C11: British | D11: UK | E11: Electrician | F11: Low | G11: =INDEX(KYC_CDD_FRAMEWORK!$K$30:$K$59,MATCH(A11,KYC_CDD_FRAMEWORK!$A$30:$A$59,0)) -> SDD | H11: 4000 | I11: Active | J11: 43329
A12: CUST011 | B12: Individual | C12: Indian | D12: UK | E12: IT Consultant | F12: Medium | G12: =INDEX(KYC_CDD_FRAMEWORK!$K$30:$K$59,MATCH(A12,KYC_CDD_FRAMEWORK!$A$30:$A$59,0)) -> CDD | H12: 7000 | I12: Active | J12: 43891
A13: CUST012 | B13: Individual | C13: Nigerian | D13: UK | E13: Import/Export | F13: Medium | G13: =INDEX(KYC_CDD_FRAMEWORK!$K$30:$K$59,MATCH(A13,KYC_CDD_FRAMEWORK!$A$30:$A$59,0)) -> EDD | H13: 12000 | I13: Active | J13: 43631
... A31: CUST030 | B31: Corporate | C31: UK Registered | D31: UK | E31: Import/Export Ltd | F31: Medium | G31: =INDEX(KYC_CDD_FRAMEWORK!$K$30:$K$59,MATCH(A31,KYC_CDD_FRAMEWORK!$A$30:$A$59,0)) -> CDD | H31: 75000 | I31: Active | J31: 43174

Sheet TRANSACTION_LEDGER
A1: Transaction_ID | B1: Date | C1: Customer_ID | D1: Transaction_Type | E1: Amount_GBP | F1: Currency | G1: Counterparty_Name | H1: Counterparty_Country | I1: Counterparty_Bank | J1: Direction | K1: Running_Balance | L1: Flagged | M1: Flag_Reason | N1: Alert_ID
A2: T001 | B2: 45292 | C2: CUST001 | D2: Salary Credit | E2: 3500 | F2: GBP | G2: City Council | H2: UK | I2: Barclays | J2: Credit | K2: 3500 | L2: NO
A3: T004 | B3: 45292 | C3: CUST002 | D3: Salary Credit | E3: 3200 | F3: GBP | G3: NHS | H3: UK | I3: Lloyds | J3: Credit | K3: 3200 | L3: NO
A4: T006 | B4: 45292 | C4: CUST003 | D4: Salary Credit | E4: 5500 | F4: GBP | G4: Tech Corp | H4: UK | I4: HSBC | J4: Credit | K4: 5500 | L4: NO
A5: T008 | B5: 45292 | C5: CUST004 | D5: Salary Credit | E5: 6000 | F5: GBP | G5: Deloitte | H5: UK | I5: NatWest | J5: Credit | K5: 6000 | L5: NO
A6: T010 | B6: 45292 | C6: CUST005 | D6: Salary Credit | E6: 3800 | F6: GBP | G6: Police Scotland | H6: UK | I6: RBS | J6: Credit | K6: 3800 | L6: NO
A7: T066 | B7: 45292 | C7: CUST006 | D7: Salary Credit | E7: 3000 | F7: GBP | G7: Tesco | H7: UK | I7: Santander | J7: Credit | K7: 3000 | L7: NO
A8: T067 | B8: 45292 | C8: CUST007 | D8: Salary Credit | E8: 4500 | F8: GBP | G8: IBM | H8: UK | I8: HSBC | J8: Credit | K8: 4500 | L8: NO
A9: T068 | B9: 45292 | C9: CUST008 | D9: Salary Credit | E9: 3300 | F9: GBP | G9: Social Services | H9: UK | I9: Barclays | J9: Credit | K9: 3300 | L9: NO
A10: T069 | B10: 45292 | C10: CUST009 | D10: Salary Credit | E10: 5000 | F10: GBP | G10: Boots Pharmacy | H10: UK | I10: Lloyds | J10: Credit | K10: 5000 | L10: NO
A11: T070 | B11: 45292 | C11: CUST010 | D11: Salary Credit | E11: 4000 | F11: GBP | G11: Construction Co | H11: UK | I11: NatWest | J11: Credit | K11: 4000 | L11: NO
A12: T002 | B12: 45296 | C12: CUST001 | D12: Bill Payment | E12: 850 | F12: GBP | G12: British Gas | H12: UK | I12: Barclays | J12: Debit | K12: 2650 | L12: NO
A13: T005 | B13: 45297 | C13: CUST002 | D13: Bill Payment | E13: 750 | F13: GBP | G13: Landlord | H13: UK | I13: Lloyds | J13: Debit | K13: 2450 | L13: NO
... A45: T090 | B45: 45352 | C45: CUST011 | D45: Business Income | E45: 7000 | F45: GBP | G45: Various Clients | H45: UK | I45: HSBC | J45: Credit | K45: 7000 | L45: NO
A46: T051 | B46: 45354 | C46: CUST018 | D46: Cash Deposit | E46: 9500 | F46: GBP | G46: Cash | H46: UK | I46: Branch | J46: Credit | K46: 9500 | L46: YES | M46: STRUCTURING | N46: ALT001
A47: T052 | B47: 45355 | C47: CUST018 | D47: Cash Deposit | E47: 9200 | F47: GBP | G47: Cash | H47: UK | I47: Branch | J47: Credit | K47: 18700 | L47: YES | M47: STRUCTURING | N47: ALT001
A48: T019 | B48: 45356 | C48: CUST006 | D48: Bill Payment | E48: 600 | F48: GBP | G48: Landlord | H48: UK | I48: Santander | J48: Debit | K48: 2400 | L48: NO
A49: T091 | B49: 45356 | C49: CUST016 | D49: Salary Credit | E49: 4500 | F49: GBP | G49: Construction Ltd | H49: UK | I49: Barclays | J49: Credit | K49: 4500 | L49: NO
A50: T053 | B50: 45358 | C50: CUST018 | D50: Cash Deposit | E50: 9800 | F50: GBP | G50: Cash | H50: UK | I50: Branch | J50: Credit | K50: 28500 | L50: YES | M50: STRUCTURING | N50: ALT001
A51: T092 | B51: 45361 | C51: CUST017 | D51: Business Income | E51: 20000 | F51: GBP | G51: Transfer Clients | H51: UK | I51: Barclays | J51: Credit | K51: 20000 | L51: NO
A52: T093 | B52: 45366 | C52: CUST019 | D52: Business Income | E52: 50000 | F52: GBP | G52: Property Sales | H52: UK | I52: HSBC | J52: Credit | K52: 50000 | L52: NO
A53: T094 | B53: 45371 | C53: CUST020 | D53: Salary Credit | E53: 30000 | F53: GBP | G53: Consultancy Co | H53: UK | I53: Barclays | J53: Credit | K53: 30000 | L53: NO
A54: T095 | B54: 45376 | C54: CUST021 | D54: Salary Credit | E54: 15000 | F54: GBP | G54: Council | H54: UK | I54: NatWest | J54: Credit | K54: 15000 | L54: NO
A55: T021 | B55: 45383 | C55: CUST008 | D55: Salary Credit | E55: 3300 | F55: GBP | G55: Social Services | H55: UK | I55: Barclays | J55: Credit | K55: 3300 | L55: NO
A56: T023 | B56: 45383 | C56: CUST009 | D56: Salary Credit | E56: 5000 | F56: GBP | G56: Boots Pharmacy | H56: UK | I56: Lloyds | J56: Credit | K56: 5000 | L56: NO
A57: T025 | B57: 45383 | C57: CUST010 | D57: Salary Credit | E57: 4000 | F57: GBP | G57: Construction Co | H57: UK | I57: NatWest | J57: Credit | K57: 4000 | L57: NO
A58: T096 | B58: 45383 | C58: CUST001 | D58: Salary Credit | E58: 3500 | F58: GBP | G58: City Council | H58: UK | I58: Barclays | J58: Credit | K58: 3500 | L58: NO
A59: T097 | B59: 45383 | C59: CUST002 | D59: Salary Credit | E59: 3200 | F59: GBP | G59: NHS | H59: UK | I59: Lloyds | J59: Credit | K59: 3200 | L59: NO
A60: T098 | B60: 45383 | C60: CUST003 | D60: Salary Credit | E60: 5500 | F60: GBP | G60: Tech Corp | H60: UK | I60: HSBC | J60: Credit | K60: 5500 | L60: NO
A61: T099 | B61: 45383 | C61: CUST005 | D61: Salary Credit | E61: 3800 | F61: GBP | G61: Police Scotland | H61: UK | I61: RBS | J61: Credit | K61: 3800 | L61: NO
A62: T100 | B62: 45383 | C62: CUST006 | D62: Salary Credit | E62: 3000 | F62: GBP | G62: Tesco | H62: UK | I62: Santander | J62: Credit | K62: 3000 | L62: NO
... A66: T102 | B66: 45392 | C66: CUST012 | D66: Bill Payment | E66: 3000 | F66: GBP | G66: Warehouse | H66: UK | I66: Barclays | J66: Debit | K66: 9000 | L66: NO
A67: T054 | B67: 45397 | C67: CUST007 | D67: Wire Transfer IN | E67: 45000 | F67: GBP | G67: Al Maktoum Trading | H67: UAE | I67: Emirates NBD | J67: Credit | K67: 45000 | L67: YES | M67: RAPID IN-OUT | N67: ALT002
A68: T103 | B68: 45397 | C68: CUST013 | D68: Bill Payment | E68: 1200 | F68: GBP | G68: Supplier | H68: UK | I68: NatWest | J68: Debit | K68: 13800 | L68: NO
A69: T055 | B69: 45398 | C69: CUST007 | D69: Wire Transfer OUT | E69: 44500 | F69: GBP | G69: Baltik UAB | H69: Lithuania | I69: SEB Bank | J69: Debit | K69: 500 | L69: YES | M69: RAPID IN-OUT | N69: ALT002
A70: T104 | B70: 45402 | C70: CUST014 | D70: Mortgage Payment | E70: 8000 | F70: GBP | G70: Santander | H70: UK | I70: HSBC | J70: Debit | K70: 17000 | L70: NO
A71: T105 | B71: 45410 | C71: CUST015 | D71: Cash Deposit | E71: 3500 | F71: GBP | G71: Cash | H71: UK | I71: Branch | J71: Credit | K71: 3500 | L71: NO
A72: T026 | B72: 45413 | C72: CUST001 | D72: Salary Credit | E72: 3500 | F72: GBP | G72: City Council | H72: UK | I72: Barclays | J72: Credit | K72: 3500 | L72: NO
A73: T027 | B73: 45413 | C73: CUST002 | D73: Salary Credit | E73: 3200 | F73: GBP | G73: NHS | H73: UK | I73: Lloyds | J73: Credit | K73: 3200 | L73: NO
A74: T028 | B74: 45413 | C74: CUST003 | D74: Salary Credit | E74: 5500 | F74: GBP | G74: Tech Corp | H74: UK | I74: HSBC | J74: Credit | K74: 5500 | L74: NO
A75: T029 | B75: 45413 | C75: CUST011 | D75: Business Income | E75: 7000 | F75: GBP | G75: Various Clients | H75: UK | I75: HSBC | J75: Credit | K75: 7000 | L75: NO
A76: T031 | B76: 45413 | C76: CUST012 | D76: Business Income | E76: 12000 | F76: GBP | G76: Import Clients | H76: Nigeria | I76: Zenith Bank | J76: Credit | K76: 12000 | L76: NO
A77: T106 | B77: 45413 | C77: CUST004 | D77: Salary Credit | E77: 6000 | F77: GBP | G77: Deloitte | H77: UK | I77: NatWest | J77: Credit | K77: 6000 | L77: NO
A78: T107 | B78: 45413 | C78: CUST005 | D78: Salary Credit | E78: 3800 | F78: GBP | G78: Police Scotland | H78: UK | I78: RBS | J78: Credit | K78: 3800 | L78: NO
A79: T108 | B79: 45413 | C79: CUST006 | D79: Salary Credit | E79: 3000 | F79: GBP | G79: Tesco | H79: UK | I79: Santander | J79: Credit | K79: 3000 | L79: NO
A80: T109 | B80: 45413 | C80: CUST007 | D80: Salary Credit | E80: 4500 | F80: GBP | G80: IBM | H80: UK | I80: HSBC | J80: Credit | K80: 4500 | L80: NO
A81: T110 | B81: 45413 | C81: CUST008 | D81: Salary Credit | E81: 3300 | F81: GBP | G81: Social Services | H81: UK | I81: Barclays | J81: Credit | K81: 3300 | L81: NO
... A87: T114 | B87: 45432 | C87: CUST020 | D87: Consultancy Fee | E87: 10000 | F87: GBP | G87: Client | H87: UK | I87: Barclays | J87: Credit | K87: 10000 | L87: NO
A88: T056 | B88: 45434 | C88: CUST012 | D88: SWIFT Transfer | E88: 28000 | F88: GBP | G88: Tehran Trading Co | H88: Iran | I88: Bank Mellat | J88: Debit | K88: 5000 | L88: YES | M88: HIGH RISK JURISDICTION | N88: ALT003
A89: T115 | B89: 45437 | C89: CUST021 | D89: Salary Credit | E89: 15000 | F89: GBP | G89: Council | H89: UK | I89: NatWest | J89: Credit | K89: 15000 | L89: NO
A90: T033 | B90: 45444 | C90: CUST013 | D90: Business Income | E90: 15000 | F90: GBP | G90: Restaurant Sales | H90: UK | I90: NatWest | J90: Credit | K90: 15000 | L90: NO
A91: T035 | B91: 45444 | C91: CUST004 | D91: Salary Credit | E91: 6000 | F91: GBP | G91: Deloitte | H91: UK | I91: NatWest | J91: Credit | K91: 6000 | L91: NO
A92: T036 | B92: 45444 | C92: CUST005 | D92: Salary Credit | E92: 3800 | F92: GBP | G92: Police Scotland | H92: UK | I92: RBS | J92: Credit | K92: 3800 | L92: NO
A93: T116 | B93: 45444 | C93: CUST001 | D93: Salary Credit | E93: 3500 | F93: GBP | G93: City Council | H93: UK | I93: Barclays | J93: Credit | K93: 3500 | L93: NO
A94: T117 | B94: 45444 | C94: CUST002 | D94: Salary Credit | E94: 3200 | F94: GBP | G94: NHS | H94: UK | I94: Lloyds | J94: Credit | K94: 3200 | L94: NO
A95: T118 | B95: 45444 | C95: CUST003 | D95: Salary Credit | E95: 5500 | F95: GBP | G95: Tech Corp | H95: UK | I95: HSBC | J95: Credit | K95: 5500 | L95: NO
A96: T119 | B96: 45444 | C96: CUST007 | D96: Salary Credit | E96: 4500 | F96: GBP | G96: IBM | H96: UK | I96: HSBC | J96: Credit | K96: 4500 | L96: NO
A97: T120 | B97: 45444 | C97: CUST008 | D97: Salary Credit | E97: 3300 | F97: GBP | G97: Social Services | H97: UK | I97: Barclays | J97: Credit | K97: 3300 | L97: NO
A98: T121 | B98: 45448 | C98: CUST011 | D98: Business Income | E98: 7000 | F98: GBP | G98: Various Clients | H98: UK | I98: HSBC | J98: Credit | K98: 7000 | L98: NO
A99: T034 | B99: 45453 | C99: CUST013 | D99: Staff Wages | E99: 4000 | F99: GBP | G99: Employees | H99: UK | I99: NatWest | J99: Debit | K99: 11000 | L99: NO
A100: T057 | B100: 45453 | C100: CUST025 | D100: Wire Transfer IN | E100: 75000 | F100: GBP | G100: Unknown Source | H100: UK | I100: Unknown | J100: Credit | K100: 75000 | L100: YES | M100: DORMANT ACCOUNT | N100: ALT004
A101: T122 | B101: 45453 | C101: CUST012 | D101: Business Income | E101: 12000 | F101: GBP | G101: Import Clients | H101: Nigeria | I101: Zenith Bank | J101: Credit | K101: 12000 | L101: NO
A102: T058 | B102: 45454 | C102: CUST025 | D102: Wire Transfer OUT | E102: 25000 | F102: GBP | G102: Multiple Accounts | H102: UK | I102: Various | J102: Debit | K102: 50000 | L102: YES | M102: DORMANT ACCOUNT | N102: ALT004
A103: T123 | B103: 45458 | C103: CUST013 | D103: Business Income | E103: 15000 | F103: GBP | G103: Restaurant Sales | H103: UK | I103: NatWest | J103: Credit | K103: 15000 | L103: NO
A104: T124 | B104: 45463 | C104: CUST014 | D104: Property Income | E104: 25000 | F104: GBP | G104: Tenants | H104: UK | I104: HSBC | J104: Credit | K104: 25000 | L104: NO
A105: T125 | B105: 45471 | C105: CUST015 | D105: Cash Deposit | E105: 4000 | F105: GBP | G105: Cash | H105: UK | I105: Branch | J105: Credit | K105: 4000 | L105: NO
A106: T037 | B106: 45474 | C106: CUST001 | D106: Salary Credit | E106: 3500 | F106: GBP | G106: City Council | H106: UK | I106: Barclays | J106: Credit | K106: 3500 | L106: NO
A107: T038 | B107: 45474 | C107: CUST009 | D107: Salary Credit | E107: 5000 | F107: GBP | G107: Boots Pharmacy | H107: UK | I107: Lloyds | J107: Credit | K107: 5000 | L107: NO
A108: T039 | B108: 45474 | C108: CUST010 | D108: Salary Credit | E108: 4000 | F108: GBP | G108: Construction Co | H108: UK | I108: NatWest | J108: Credit | K108: 4000 | L108: NO
A109: T040 | B109: 45474 | C109: CUST014 | D109: Property Income | E109: 25000 | F109: GBP | G109: Tenants | H109: UK | I109: HSBC | J109: Credit | K109: 25000 | L109: NO
A110: T126 | B110: 45474 | C110: CUST002 | D110: Salary Credit | E110: 3200 | F110: GBP | G110: NHS | H110: UK | I110: Lloyds | J110: Credit | K110: 3200 | L110: NO
A111: T127 | B111: 45474 | C111: CUST003 | D111: Salary Credit | E111: 5500 | F111: GBP | G111: Tech Corp | H111: UK | I111: HSBC | J111: Credit | K111: 5500 | L111: NO
A112: T128 | B112: 45474 | C112: CUST004 | D112: Salary Credit | E112: 6000 | F112: GBP | G112: Deloitte | H112: UK | I112: NatWest | J112: Credit | K112: 6000 | L112: NO
A113: T129 | B113: 45474 | C113: CUST005 | D113: Salary Credit | E113: 3800 | F113: GBP | G113: Police Scotland | H113: UK | I113: RBS | J113: Credit | K113: 3800 | L113: NO
A114: T130 | B114: 45474 | C114: CUST006 | D114: Salary Credit | E114: 3000 | F114: GBP | G114: Tesco | H114: UK | I114: Santander | J114: Credit | K114: 3000 | L114: NO
... A118: T133 | B118: 45488 | C118: CUST013 | D118: Staff Wages | E118: 4000 | F118: GBP | G118: Employees | H118: UK | I118: NatWest | J118: Debit | K118: 11000 | L118: NO
A119: T059 | B119: 45491 | C119: CUST021 | D119: Wire Transfer IN | E119: 120000 | F119: GBP | G119: Offshore Holdings Ltd | H119: Cayman Islands | I119: Cayman National | J119: Credit | K119: 120000 | L119: YES | M119: PEP TRANSACTION | N119: ALT005
A120: T134 | B120: 45493 | C120: CUST016 | D120: Salary Credit | E120: 4500 | F120: GBP | G120: Construction Ltd | H120: UK | I120: Barclays | J120: Credit | K120: 4500 | L120: NO
A121: T135 | B121: 45498 | C121: CUST017 | D121: Business Income | E121: 20000 | F121: GBP | G121: Transfer Clients | H121: UK | I121: Barclays | J121: Credit | K121: 20000 | L121: NO
A122: T042 | B122: 45505 | C122: CUST001 | D122: Salary Credit | E122: 3500 | F122: GBP | G122: City Council | H122: UK | I122: Barclays | J122: Credit | K122: 3500 | L122: NO
A123: T043 | B123: 45505 | C123: CUST002 | D123: Salary Credit | E123: 3200 | F123: GBP | G123: NHS | H123: UK | I123: Lloyds | J123: Credit | K123: 3200 | L123: NO
A124: T044 | B124: 45505 | C124: CUST016 | D124: Salary Credit | E124: 4500 | F124: GBP | G124: Construction Ltd | H124: UK | I124: Barclays | J124: Credit | K124: 4500 | L124: NO
A125: T136 | B125: 45505 | C125: CUST003 | D125: Salary Credit | E125: 5500 | F125: GBP | G125: Tech Corp | H125: UK | I125: HSBC | J125: Credit | K125: 5500 | L125: NO
A126: T137 | B126: 45505 | C126: CUST004 | D126: Salary Credit | E126: 6000 | F126: GBP | G126: Deloitte | H126: UK | I126: NatWest | J126: Credit | K126: 6000 | L126: NO
A127: T138 | B127: 45505 | C127: CUST005 | D127: Salary Credit | E127: 3800 | F127: GBP | G127: Police Scotland | H127: UK | I127: RBS | J127: Credit | K127: 3800 | L127: NO
A128: T139 | B128: 45505 | C128: CUST006 | D128: Salary Credit | E128: 3000 | F128: GBP | G128: Tesco | H128: UK | I128: Santander | J128: Credit | K128: 3000 | L128: NO
A129: T140 | B129: 45505 | C129: CUST007 | D129: Salary Credit | E129: 4500 | F129: GBP | G129: IBM | H129: UK | I129: HSBC | J129: Credit | K129: 4500 | L129: NO
A130: T060 | B130: 45506 | C130: CUST022 | D130: Wire Transfer OUT | E130: 30000 | F130: GBP | G130: CUST019 | H130: UK | I130: Barclays | J130: Debit | K130: 10000 | L130: YES | M130: ROUND TRIPPING | N130: ALT006
A131: T141 | B131: 45509 | C131: CUST011 | D131: Business Income | E131: 7000 | F131: GBP | G131: Various Clients | H131: UK | I131: HSBC | J131: Credit | K131: 7000 | L131: NO
A132: T061 | B132: 45513 | C132: CUST019 | D132: Wire Transfer OUT | E132: 29500 | F132: GBP | G132: CUST022 | H132: UK | I132: Barclays | J132: Debit | K132: 5000 | L132: YES | M132: ROUND TRIPPING | N132: ALT006
A133: T045 | B133: 45514 | C133: CUST016 | D133: Wire Transfer | E133: 1000 | F133: GBP | G133: Family | H133: Romania | I133: ING | J133: Debit | K133: 3500 | L133: NO
A134: T142 | B134: 45514 | C134: CUST012 | D134: Business Income | E134: 12000 | F134: GBP | G134: Import Clients | H134: Nigeria | I134: Zenith Bank | J134: Credit | K134: 12000 | L134: NO
A135: T143 | B135: 45519 | C135: CUST013 | D135: Business Income | E135: 15000 | F135: GBP | G135: Restaurant Sales | H135: UK | I135: NatWest | J135: Credit | K135: 15000 | L135: NO
A136: T144 | B136: 45524 | C136: CUST019 | D136: Property Income | E136: 50000 | F136: GBP | G136: Tenants | H136: UK | I136: HSBC | J136: Credit | K136: 50000 | L136: NO
A137: T145 | B137: 45532 | C137: CUST020 | D137: Consultancy Fee | E137: 10000 | F137: GBP | G137: Client | H137: UK | I137: Barclays | J137: Credit | K137: 10000 | L137: NO
A138: T046 | B138: 45536 | C138: CUST003 | D138: Salary Credit | E138: 5500 | F138: GBP | G138: Tech Corp | H138: UK | I138: HSBC | J138: Credit | K138: 5500 | L138: NO
A139: T047 | B139: 45536 | C139: CUST017 | D139: Business Income | E139: 20000 | F139: GBP | G139: Transfer Clients | H139: UK | I139: Barclays | J139: Credit | K139: 20000 | L139: NO
A140: T146 | B140: 45536 | C140: CUST001 | D140: Salary Credit | E140: 3500 | F140: GBP | G140: City Council | H140: UK | I140: Barclays | J140: Credit | K140: 3500 | L140: NO
A141: T147 | B141: 45536 | C141: CUST002 | D141: Salary Credit | E141: 3200 | F141: GBP | G141: NHS | H141: UK | I141: Lloyds | J141: Credit | K141: 3200 | L141: NO
A142: T148 | B142: 45536 | C142: CUST004 | D142: Salary Credit | E142: 6000 | F142: GBP | G142: Deloitte | H142: UK | I142: NatWest | J142: Credit | K142: 6000 | L142: NO
...

Sheet ALERT_INVESTIGATION_LOG
A1: CALEDONIA BANK PLC — ALERT INVESTIGATION LOG
A2: Regulatory framework: MLR 2017 | JMLSG 2026 | POCA 2002 | FCA Financial Crime Guide | All alerts FY2024
A4: ALERT_ID | B4: DATE_RAISED | C4: CUSTOMER_ID | D4: OCCUPATION | E4: ALERT_TYPE | F4: TM_RULE_TRIGGERED | G4: TRANSACTION_REF | H4: AMOUNT_GBP | I4: PRIORITY | J4: ASSIGNED_TO | K4: DATE_CLOSED | L4: DISPOSITION | M4: SAR_FILED | N4: NOTES
A5: ALT001 | B5: 45358 | C5: CUST018 | D5: Market Trader | E5: Structuring | F5: TM-001 | G5: T051, T052, T053 | H5: 28500 | I5: HIGH | J5: AML Analyst | K5: 45366 | L5: TRUE POSITIVE | M5: YES | N5: 3 cash deposits £9,500/£9,200/£9,800 in 5 days. 356% of monthly turnover. SAR filed.
A6: ALT002 | B6: 45398 | C6: CUST007 | D6: IT Analyst | E6: Rapid In-Out | F6: TM-002 | G6: T054, T055 | H6: 45000 | I6: HIGH | J6: AML Analyst | K6: 45407 | L6: TRUE POSITIVE | M6: YES | N6: £45,000 in from UAE, £44,500 out to Lithuania within 24hrs. 98.9% pass-through. SAR filed.
A7: ALT003 | B7: 45434 | C7: CUST012 | D7: Import/Export | E7: High Risk Jurisdiction | F7: TM-003 | G7: T056 | H7: 28000 | I7: HIGH | J7: AML Analyst | K7: 45442 | L7: TRUE POSITIVE | M7: YES | N7: SWIFT transfer to Tehran Trading Co, Iran. FATF high-risk jurisdiction. SAR filed.
A8: ALT004 | B8: 45453 | C8: CUST025 | D8: Jewellery Trader | E8: Dormant Account Activity | F8: TM-004 | G8: T057, T058 | H8: 75000 | I8: HIGH | J8: AML Analyst | K8: 45463 | L8: TRUE POSITIVE | M8: YES | N8: Account dormant 3+ years. £75,000 credit from unknown source. Immediate layering detected. SAR filed.
A9: ALT005 | B9: 45491 | C9: CUST021 | D9: Local Council Leader | E9: PEP High Value | F9: TM-005 | G9: T059 | H9: 120000 | I9: HIGH | J9: AML Analyst | L9: PENDING | M9: NO | N9: PEP received £120,000 from Cayman Islands offshore entity. EDD review ongoing. Awaiting senior management approval.
A10: ALT006 | B10: 45513 | C10: CUST022 | D10: Import/Export | E10: Round Tripping | F10: TM-007 | G10: T060, T061 | H10: 30000 | I10: HIGH | J10: AML Analyst | K10: 45524 | L10: FALSE POSITIVE | M10: NO | N10: Funds returned between linked accounts — confirmed legitimate loan repayment between family members. Documented and closed.
A11: ALT007 | B11: 45549 | C11: CUST015 | D11: Market Trader | E11: Cash Intensity | F11: TM-006 | G11: T062 | H11: 18000 | I11: MEDIUM | J11: AML Analyst | K11: 45560 | L11: FALSE POSITIVE | M11: NO | N11: Cash deposit 225% of monthly turnover. Customer provided market trading invoices and receipts. Legitimate seasonal income.
A12: ALT008 | B12: 45586 | C12: CUST028 | D12: Logistics Manager | E12: Sanctions Screening | F12: TM-008 | G12: T063, T064 | H12: 23500 | I12: CRITICAL | J12: AML Analyst | K12: 45616 | L12: TRUE POSITIVE | M12: YES | N12: SWIFT transfers to Russia and Belarus — OFSI sanctioned jurisdictions. Account frozen immediately. MLRO notified within 2 hours. SAR filed same day.
A13: ALT009 | B13: 45599 | C13: CUST015 | D13: Market Trader | E13: Structuring | F13: TM-001 | G13: T065 | H13: 9700 | I13: MEDIUM | J13: AML Analyst | K13: 45608 | L13: WHITELISTED | M13: NO | N13: Single cash deposit £9,700. Reviewed in context of ALT007 — consistent with seasonal trading pattern. Whitelisted with 6-month review.
A14: ALT010 | B14: 45656 | C14: CUST029 | D14: Holding Company | E14: Complex Corporate Structure | F14: TM-009 | G14: T198, T199 | H14: 100000 | I14: HIGH | J14: AML Analyst | L14: PENDING | M14: NO | N14: £100,000 corporate credit followed by £50,000 intercompany transfer. Complex ownership structure under review. UBO verification outstanding.
A17: ALERT DISPOSITION SUMMARY — FY2024
A18: KEY METRICS | E18: PRIORITY BREAKDOWN | I18: SAR METRICS
A19: Total Alerts Reviewed | C19: =COUNTA(A5:A14) -> 10 | E19: CRITICAL | F19: =COUNTIF(I5:I14,"CRITICAL") -> 1 | I19: Total SARs Filed | K19: =COUNTIF(M5:M14,"YES") -> 5
A20: True Positives | C20: =COUNTIF(L5:L14,"TRUE POSITIVE") -> 5 | E20: HIGH | F20: =COUNTIF(I5:I14,"HIGH") -> 7 | I20: SAR Filing Rate | K20: =COUNTIF(M5:M14,"YES")/COUNTA(M5:M14) -> 0.5
A21: False Positives | C21: =COUNTIF(L5:L14,"FALSE POSITIVE") -> 2 | E21: MEDIUM | F21: =COUNTIF(I5:I14,"MEDIUM") -> 2 | I21: Avg Days to Close | K21: =AVERAGEIF(L5:L14,"TRUE POSITIVE",K5:K14)-AVERAGEIF(L5:L14,"TRUE POSITIVE",B5:B14) -> 13
A22: Pending Investigation | C22: =COUNTIF(L5:L14,"PENDING") -> 2 | I22: Sanctions SARs | K22: =COUNTIF(E5:E14,"Sanctions Screening") -> 1
A23: Whitelisted | C23: =COUNTIF(L5:L14,"WHITELISTED") -> 1
A24: SARs Filed | C24: =COUNTIF(M5:M14,"YES") -> 5
A25: False Positive Rate | C25: =COUNTIF(L5:L14,"FALSE POSITIVE")/COUNTA(L5:L14) -> 0.2
A26: Critical Alerts | C26: =COUNTIF(I5:I14,"CRITICAL") -> 1
A30: TRUE POSITIVE | B30: =COUNTIF(L5:L14,"TRUE POSITIVE") -> 5
A31: FALSE POSITIVE | B31: =COUNTIF(L5:L14,"FALSE POSITIVE") -> 2
A32: PENDING | B32: =COUNTIF(L5:L14,"PENDING") -> 2
A33: WHITELISTED | B33: =COUNTIF(L5:L14,"WHITELISTED") -> 1
A49: Note: False Positive Rate of 20% is within acceptable industry range (15-25%). SAR filing rate of 50% reflects conservative approach aligned to JMLSG 2026 guidance. All SARs submitted to NCA within 7 working days per POCA 2002 Section 330.

Sheet KYC_CDD_FRAMEWORK
A1: CALEDONIA BANK PLC — KYC/CDD RISK ASSESSMENT FRAMEWORK
A2: Regulatory basis: MLR 2017 Regulations 28, 33 & 40 | JMLSG Guidance 2026 Part I Chapter 5 | FCA Financial Crime Guide
A4: SECTION 1 — CDD TIER DEFINITIONS
A5: CDD TIER | B5: REGULATORY BASIS | C5: CUSTOMER TYPE | D5: REVIEW FREQUENCY | E5: KEY REQUIREMENTS
A6: SDD (Simplified Due Diligence) | B6: MLR 2017 Reg 37 | C6: UK/EEA regulated firms, listed companies, public authorities, and low-risk retail customers scoring ≤ 20 points | D6: 3 years | E6: Verify entity type, confirm regulatory status, no source of funds required
A7: CDD (Customer Due Diligence) | B7: MLR 2017 Reg 28 | C7: Standard retail and business customers | D7: 1-2 years | E7: Photo ID, proof of address, source of funds for transactions >£10,000
A8: EDD (Enhanced Due Diligence) | B8: MLR 2017 Reg 33 | C8: PEPs, high-risk countries, complex structures, cash-intensive | D8: 6 months | E8: Source of wealth, senior management approval, ongoing monitoring, adverse media
A10: SECTION 2 — CUSTOMER RISK SCORING MODEL
A11: Total score out of 100 points across 5 risk dimensions. Higher score = higher risk. Score determines CDD tier assignment.
A12: RISK DIMENSION | B12: MAX SCORE | C12: SCORING CRITERIA | D12: WEIGHT
A13: Country Risk | B13: 30 | C13: UK/EEA = 0-5pts, Standard = 6-15pts, FATF Grey List = 16-25pts, FATF High Risk = 26-30pts | D13: 0.3
A14: Customer Type | B14: 25 | C14: Salaried individual = 0-5pts, Self-employed = 6-15pts, PEP/HNW = 16-22pts, Cash business = 23-25pts | D14: 0.25
A15: Product Risk | B15: 20 | C15: Standard current account = 0-5pts, Business account = 6-12pts, International payments = 13-17pts, Private banking = 18-20pts | D15: 0.2
A16: Transaction Behaviour | B16: 15 | C16: Expected pattern = 0-3pts, Minor anomalies = 4-8pts, Significant anomalies = 9-12pts, Structuring/layering = 13-15pts | D16: 0.15
A17: Adverse Information | B17: 10 | C17: None = 0pts, Minor = 1-4pts, Significant = 5-7pts, Sanctions/PEP/Criminal = 8-10pts | D17: 0.1
A18: TOTAL | B18: 100 | D18: 1
A20: SECTION 3 — CDD TIER ASSIGNMENT
A21: TOTAL SCORE RANGE | B21: CDD TIER | C21: RISK LEVEL | D21: ACTION REQUIRED
A22: 0 — 20 | B22: SDD | C22: LOW | D22: Simplified Due Diligence. 3-year review. Confirm regulated status only.
A23: 21 — 50 | B23: CDD | C23: MEDIUM | D23: Standard Customer Due Diligence. Annual review. Photo ID and proof of address.
A24: 51 — 75 | B24: EDD | C24: HIGH | D24: Enhanced Due Diligence required. 6-monthly review. Source of wealth mandatory.
A25: 76 — 100 | B25: EDD Urgent | C25: CRITICAL | D25: Immediate senior management review. Consider account closure. File SAR if suspicious.
A27: SECTION 4 — CUSTOMER RISK REGISTER
A28: Risk scores applied to all 30 Caledonia Bank customers. CDD tier assigned based on Section 3 scoring model.
A29: CUSTOMER_ID | B29: CUSTOMER_NAME | C29: NATIONALITY | D29: OCCUPATION | E29: COUNTRY RISK | F29: CUSTOMER TYPE | G29: PRODUCT RISK | H29: TXN BEHAVIOUR | I29: ADVERSE INFO | J29: TOTAL SCORE | K29: TIER
A30: CUST001 | B30: Individual | C30: British | D30: Teacher | E30: 3 | F30: 0 | G30: 0 | H30: 0 | I30: 0 | J30: =SUM(E30:I30) -> 3 | K30: =IF(J30>=76,"EDD Urgent",IF(J30>=51,"EDD",IF(J30>=21,"CDD","SDD"))) -> SDD
A31: CUST002 | B31: Individual | C31: British | D31: Nurse | E31: 3 | F31: 0 | G31: 0 | H31: 0 | I31: 0 | J31: =SUM(E31:I31) -> 3 | K31: =IF(J31>=76,"EDD Urgent",IF(J31>=51,"EDD",IF(J31>=21,"CDD","SDD"))) -> SDD
A32: CUST003 | B32: Individual | C32: British | D32: Engineer | E32: 3 | F32: 0 | G32: 0 | H32: 0 | I32: 0 | J32: =SUM(E32:I32) -> 3 | K32: =IF(J32>=76,"EDD Urgent",IF(J32>=51,"EDD",IF(J32>=21,"CDD","SDD"))) -> SDD
A33: CUST004 | B33: Individual | C33: British | D33: Accountant | E33: 3 | F33: 0 | G33: 0 | H33: 0 | I33: 0 | J33: =SUM(E33:I33) -> 3 | K33: =IF(J33>=76,"EDD Urgent",IF(J33>=51,"EDD",IF(J33>=21,"CDD","SDD"))) -> SDD
A34: CUST005 | B34: Individual | C34: British | D34: Police Officer | E34: 3 | F34: 0 | G34: 0 | H34: 0 | I34: 0 | J34: =SUM(E34:I34) -> 3 | K34: =IF(J34>=76,"EDD Urgent",IF(J34>=51,"EDD",IF(J34>=21,"CDD","SDD"))) -> SDD
A35: CUST006 | B35: Individual | C35: British | D35: Retail Manager | E35: 3 | F35: 0 | G35: 0 | H35: 0 | I35: 0 | J35: =SUM(E35:I35) -> 3 | K35: =IF(J35>=76,"EDD Urgent",IF(J35>=51,"EDD",IF(J35>=21,"CDD","SDD"))) -> SDD
A36: CUST007 | B36: Individual | C36: British | D36: IT Analyst | E36: 3 | F36: 0 | G36: 12 | H36: 9 | I36: 0 | J36: =SUM(E36:I36) -> 24 | K36: =IF(J36>=76,"EDD Urgent",IF(J36>=51,"EDD",IF(J36>=21,"CDD","SDD"))) -> CDD
A37: CUST008 | B37: Individual | C37: British | D37: Social Worker | E37: 3 | F37: 0 | G37: 0 | H37: 0 | I37: 0 | J37: =SUM(E37:I37) -> 3 | K37: =IF(J37>=76,"EDD Urgent",IF(J37>=51,"EDD",IF(J37>=21,"CDD","SDD"))) -> SDD
A38: CUST009 | B38: Individual | C38: British | D38: Pharmacist | E38: 3 | F38: 0 | G38: 0 | H38: 0 | I38: 0 | J38: =SUM(E38:I38) -> 3 | K38: =IF(J38>=76,"EDD Urgent",IF(J38>=51,"EDD",IF(J38>=21,"CDD","SDD"))) -> SDD
A39: CUST010 | B39: Individual | C39: British | D39: Electrician | E39: 3 | F39: 0 | G39: 0 | H39: 0 | I39: 0 | J39: =SUM(E39:I39) -> 3 | K39: =IF(J39>=76,"EDD Urgent",IF(J39>=51,"EDD",IF(J39>=21,"CDD","SDD"))) -> SDD
A40: CUST011 | B40: Individual | C40: Indian | D40: IT Consultant | E40: 8 | F40: 7 | G40: 12 | H40: 3 | I40: 0 | J40: =SUM(E40:I40) -> 30 | K40: =IF(J40>=76,"EDD Urgent",IF(J40>=51,"EDD",IF(J40>=21,"CDD","SDD"))) -> CDD
A41: CUST012 | B41: Individual | C41: Nigerian | D41: Import/Export | E41: 16 | F41: 13 | G41: 12 | H41: 9 | I41: 5 | J41: =SUM(E41:I41) -> 55 | K41: =IF(J41>=76,"EDD Urgent",IF(J41>=51,"EDD",IF(J41>=21,"CDD","SDD"))) -> EDD
... A59: CUST030 | B59: Corporate | C59: UK Registered | D59: Import/Export Ltd | E59: 3 | F59: 17 | G59: 16 | H59: 9 | I59: 0 | J59: =SUM(E59:I59) -> 45 | K59: =IF(J59>=76,"EDD Urgent",IF(J59>=51,"EDD",IF(J59>=21,"CDD","SDD"))) -> CDD

Sheet TM_RULES_SUMMARY
A1: CALEDONIA BANK PLC — TRANSACTION MONITORING RULES SUMMARY
A2: Regulatory basis: MLR 2017 | JMLSG 2026 | POCA 2002 | FCA Financial Crime Guide | OFSI | 9 Active Rules | Last reviewed: 23/06/2026
A3: RULES OVERVIEW
A4: RULE_ID | B4: RULE_NAME | C4: TYPOLOGY | D4: TRIGGER CONDITIONS | E4: THRESHOLD | F4: PRIORITY | G4: REGULATORY BASIS | H4: ACTION REQUIRED | I4: ALERTS TRIGGERED FY2024 | J4: TRUE POSITIVE RATE
A5: TM-001 | B5: Structuring / Smurfing | C5: Money Laundering — Placement | D5: 3 or more cash deposits between £8,000-£9,999 within 30 days, or any single cash deposit of £9,500 or above | E5: £8,000 — £9,999 per transaction | F5: HIGH | G5: MLR 2017 Reg 28 | JMLSG Part I 6.13 | H5: Review transaction history. File SAR if no legitimate explanation. | I5: 2 | J5: 0.5
A6: TM-002 | B6: Rapid In-Out / Pass Through | C6: Money Laundering — Layering | D6: Credit >£10,000 followed by 80%+ debit within 48 hours | E6: >£10,000 credit, >80% debited within 48hrs | F6: HIGH | G6: MLR 2017 Reg 28 | JMLSG Part I 6.14 | H6: Freeze account pending investigation. Verify source of funds. | I6: 1 | J6: 1
A7: TM-003 | B7: High Risk Jurisdiction Transfer | C7: Money Laundering — Layering | D7: Any transaction to/from a FATF high-risk jurisdiction (call-for-action list) | E7: Any amount | F7: HIGH | G7: MLR 2017 Reg 33 | FATF Recommendations 18-21 | H7: Apply EDD. Verify purpose of transfer. Escalate to MLRO. | I7: 1 | J7: 1
A8: TM-004 | B8: Dormant Account Reactivation | C8: Money Laundering — Placement | D8: Any transaction >£5,000 on account dormant 12+ months | E8: >£5,000 on dormant account | F8: HIGH | G8: MLR 2017 Reg 28 | JMLSG Part I 6.22 | H8: Contact customer. Verify source of funds. Re-KYC required. | I8: 1 | J8: 1
A9: TM-005 | B9: PEP High Value Transaction | C9: Bribery / Corruption | D9: PEP customer transaction exceeding £50,000 | E9: >£50,000 for PEP customers | F9: HIGH | G9: MLR 2017 Reg 35 | JMLSG Part I 5.7 | H9: Senior management approval required. EDD review. Source of wealth verification. | I9: 1 | J9: Pending
A10: TM-006 | B10: Unusual Cash Intensity | C10: Money Laundering — Placement | D10: Total cash deposits exceed 200% of monthly expected turnover | E10: >200% of expected monthly turnover | F10: MEDIUM | G10: MLR 2017 Reg 28 | JMLSG Part II 4.3 | H10: Review cash source. Request business trading evidence. | I10: 1 | J10: 0
A11: TM-007 | B11: Round Tripping / Circular Funds | C11: Money Laundering — Layering | D11: Funds sent and returned between linked accounts within 14 days with <5% variance | E11: <5% variance on return within 14 days | F11: HIGH | G11: MLR 2017 Reg 28 | JMLSG Part I 6.15 | H11: Map linked accounts. Verify business purpose. Escalate if no legitimate reason. | I11: 1 | J11: 0
A12: TM-008 | B12: Sanctions Screening Hit | C12: Sanctions Evasion | D12: Counterparty country matches OFSI consolidated sanctions list | E12: Any amount to sanctioned jurisdiction | F12: CRITICAL | G12: POCA 2002 S.330 | Sanctions Act 2018 | OFSI Guidance | H12: Block transaction immediately. Freeze account. File SAR same day. Notify MLRO within 2 hours. | I12: 1 | J12: 1
A13: TM-009 | B13: Complex Corporate Structure | C13: Money Laundering — Layering | D13: Corporate credit >£50,000 followed by intercompany transfer where UBO not verified | E13: >£50,000 corporate credit, UBO unverified | F13: HIGH | G13: MLR 2017 Reg 28 | JMLSG Part I 5.3 | H13: Verify UBO and ownership structure. Map group entities. Escalate to MLRO if opacity persists. | I13: 1 | J13: Pending
A15: RULES PERFORMANCE SUMMARY — FY2024
A16: METRIC | B16: VALUE
A17: Total Active Rules | B17: =COUNTA(A5:A13) -> 9
A18: Total Alerts Generated FY2024 | B18: =SUM(I5:I13) -> 10
A19: Critical Priority Rules | B19: =COUNTIF(F5:F13,"CRITICAL") -> 1
A20: High Priority Rules | B20: =COUNTIF(F5:F13,"HIGH") -> 7
A21: Medium Priority Rules | B21: =COUNTIF(F5:F13,"MEDIUM") -> 1
A22: Overall True Positive Rate | B22: =ALERT_INVESTIGATION_LOG!C20/ALERT_INVESTIGATION_LOG!C19 -> 0.5
A23: SARs Filed | B23: =ALERT_INVESTIGATION_LOG!C24 -> 5
A24: Rules Triggered in FY2024 | B24: =COUNTIF(I5:I13,">0") -> 9
A26: NOTE: All TM rules are reviewed quarterly per JMLSG 2026 guidance. Rules are back-tested against 12 months of transaction data annually. CRITICAL rules (TM-008) trigger automatic account freeze per OFSI financial sanctions guidance. All SARs submitted to NCA within 7 working days per POCA 2002 Section 330.

Sheet SAR Report
A1: SUSPICIOUS ACTIVITY REPORT (SAR)
A2: CALEDONIA BANK PLC
A3: SUSPICIOUS ACTIVITY REPORT | SAR-2024-001 | Caledonia Bank plc | SAMPLE — SYNTHETIC DATA
A4: SAR Reference: SAR-2024-001
A5: Submitted to: National Crime Agency (NCA)
A6: Regulatory basis: POCA 2002 S.330 | MLR 2017 | JMLSG 2026
A8: Field | B8: Value
A9: SAR Reference | B9: SAR-2024-001
A10: Date of Submission | B10: 45366
A11: Submitted By | B11: AML Analyst — Financial Crime Team
A12: MLRO Sign-Off | B12: Chief Compliance Officer
A13: Alert Reference | B13: ALT001
A14: TM Rule Triggered | B14: TM-001 — Structuring / Smurfing
A15: Classification | B15: SAMPLE — SYNTHETIC DATA FOR DEMONSTRATION ONLY
A17: TIPPING OFF WARNING — POCA 2002 SECTION 333A
A18: It is a criminal offence to disclose to the subject of this report that a SAR has been filed. Penalty: up to 5 years imprisonment. DO NOT contact the customer.
A21: SECTION 1 — SUBJECT DETAILS
A22: Field | B22: Value
A23: Customer Reference | B23: CUST018
A24: Customer Name | B24: Redacted - available on secure system
A25: Customer Type | B25: Individual
A26: Occupation | B26: Market Trader
A27: Nationality | B27: British
A28: Country of Residence | B28: United Kingdom
A29: Account Status | B29: Active
A30: KYC Tier | B30: CDD (Customer Due Diligence)
A31: Risk Rating | B31: MEDIUM
A32: Monthly Expected Turnover | B32: £8,000
A33: Account Open Date | B33: =VLOOKUP(B23,CUSTOMER_PROFILES!A:J,10,FALSE) -> 43554
A34: Previous SARs | B34: None
A36: SECTION 2: SUSPICIOUS ACTIVITY
A38: The following suspicious activity was identified through the automated Transaction Monitoring system on 07 March 2024, triggering Rule TM-001 (Structuring / Smurfing).
A40: Transaction ID | B40: Date | C40: Type | D40: Amount | E40: Location | F40: Running Balance
A41: T051 | B41: 45354 | C41: Cash Deposit | D41: £9,500 | E41: Edinburgh Branch | F41: £9,500
A42: T052 | B42: 45355 | C42: Cash Deposit | D42: £9,200 | E42: Edinburgh Branch | F42: £18,700
A43: T053 | B43: 45358 | C43: Cash Deposit | D43: £9,800 | E43: Edinburgh Branch | F43: £28,500
A45: SUMMARY OF ACTIVITY:
A46: 1. Three cash deposits over 5 consecutive days totalling £28,500
A47: 2. All deposits just below £10,000 reporting threshold — classic structuring
A48: 3.Total represents 356% of monthly expected turnover of £8,000
A49: 4.Deposits made at the same branch within a 5-day period
A50: 5.No legitimate business explanation provided
A53: SECTION 3 — WHY THIS ACTIVITY IS SUSPICIOUS
A55: The following red flags were identified during the investigation of Alert ALT001:
A57: 1.SUB-THRESHOLD STRUCTURING: All three deposits deliberately structured just below £10,000. JMLSG 2026 Part I 6.13 identifies this as a primary indicator of placement activity.
A58: 2.VOLUME ANOMALY: £28,500 total represents 356% of declared monthly turnover of £8,000 — unexplained and inconsistent with occupation.
A59: 3.FREQUENCY ANOMALY: Three deposits in 5 days is inconsistent with normal transaction pattern. Historical average is £3,000-£4,000 per month.
A60: 4.COUNTERPARTY: All deposits listed as Cash with no identifiable counterparty — consistent with placement stage of money laundering.
... A67: SECTION 4 — HOW THE ACTIVITY WAS DETECTED
A68: Field | B68: Value
A69: Detection Method | B69: Automated Transaction Monitoring System
A70: TM Rule Triggered | B70: TM-001 Structuring / Smurfing
A71: Rule Logic | B71: 3+ cash deposits between £8,000-£9,999 within 30 days
A72: Alert Generated | B72: 45358
A73: Alert Reference | B73: ALT001
A74: Alert Priority | B74: HIGH
A75: Assigned To | B75: AML Analyst - Financial Crime Team
A76: Investigation Commenced | B76: 45358
A77: Investigation Completed | B77: 45366
A78: Total Investigation Time | B78: 8 days
A80: INVESTIGATION STEPS TAKEN:
A81: 1.Alert reviewed and accepted for investigation on 07/03/2024
A82: 2.Full 12-month transaction history reviewed
A83: 3.Customer profile and KYC documentation reviewed
A84: 4.PEP and sanctions screening re-run- no hits
A85: 5.Adverse media search conducted- no results
A86: 6.Prior alert history reviewed - no previous alerts on this customer
A87: 7.No innocent explanation identified - decision to file SAR
A88: 8.SAR drafted and reviewed by MLRO- approved 15/03/2024
A89: 9.SAR submitted to NCA via SARs Online portal
A91: SECTION 5 — ACTION TAKEN
A92: Field | B92: Value
A93: SAR Filed | B93: YES - SAR-2024-001
A94: Date Filed | B94: 45366
A95: Submitted To | B95: National Crime Agency via SARs Online
A96: DAML Consent Requested | B96: NO - No pending transactions
A97: Account Frozen | B97: NO - Enhanced monitoring applied
A98: Customer Notified | B98: NO - Tipping off restriction applies
A99: MLRO Notified | B99: YES - 07/03/2024
A100: Enhanced Monitoring | B100: YES - Real-time alerts activated
A101: KYC Review Required | B101: YES - Full CDD refresh within 30 days
A102: Next Review Date | B102: 45397
A104: DAML — DEFENCE AGAINST MONEY LAUNDERING
A105: A DAML consent must be obtained from the NCA before proceeding with any transaction suspected to involve criminal property. The NCA has 7 working days to respond. Proceeding without consent is a criminal offence under POCA 2002 Section 328.
A107: REGULATORY OBLIGATIONS MET:
A108: SAR filed within 7 working days per JMLSG 2026 guidance. Tipping off restriction observed throughout. MLRO approved prior to submission. All documentation retained for 5 years per MLR 2017 Regulation 40.
A110: POCA 2002 S.333A — TIPPING OFF OFFENCE APPLIES
