Workbook

Sheet COREP_OVERVIEW
A1: CALEDONIA BANK PLC — COREP CAPITAL ADEQUACY REPORTING
A3: Submitted quarterly to PRA within 30 days of period end | Framework: EBA ITS on Supervisory Reporting
A5: COREP RETURNS REFERENCE TABLE
A7: RETURN | B7: FULL NAME | C7: FREQUENCY | D7: WHAT IT COVERS | E7: REGULATORY BASIS
A8: C01 | B8: Own Funds | C8: Quarterly | D8: CET1, AT1 Capital, Tier 2 Capital, Total Own Funds | E8: EBA ITS Art 4
A9: C02 | B9: Capital Requirements | C9: Quarterly | D9: Total RWA, minimum capital ratios, capital adequacy | E9: EBA ITS Art 5
A10: C07-C09 | B10: Credit Risk | C10: Quarterly | D10: Credit RWA by exposure class — mortgages, corporate, retail | E10: Basel III Art 112
A11: C16-C18 | B11: Operational Risk | C11: Quarterly | D11: OpRisk RWA using Basic Indicator Approach — 15% x gross income | E11: Basel III Art 315
A12: C47 | B12: Leverage Ratio | C12: Quarterly | D12: Tier 1 Capital / Total Exposure Measure — minimum 3.5% | E12: UK LRF 2015

Sheet EXTERNAL_INPUTS
A1: CALEDONIA BANK PLC — EXTERNAL INPUTS FROM FPA_PL_Model.xlsx
A2: All external links to the FPA model are consolidated on this sheet. Downstream sheets reference these cells only.
A4: SECTION A — P&L ITEMS (PL_MODEL, £m)
A5: ITEM | B5: FY2022 | C5: FY2023 | D5: FY2024 | E5: SOURCE ROW
A6: Interest Income | C6: =[1]PL_MODEL!$F$4 -> 8909.6478 | D6: =[1]PL_MODEL!$G$4 -> 9864.6135 | E6: PL_MODEL row 4
A7: Interest Expense | C7: =[1]PL_MODEL!$F$5 -> 4521.2886 | D7: =[1]PL_MODEL!$G$5 -> 5110.5543 | E7: PL_MODEL row 5
A8: Net Interest Income | C8: =[1]PL_MODEL!$F$6 -> 4388.3592 | D8: =[1]PL_MODEL!$G$6 -> 4754.0592 | E8: PL_MODEL row 6
A9: Fee and Commission Income | C9: =[1]PL_MODEL!$F$7 -> 576.90961 | D9: =[1]PL_MODEL!$G$7 -> 597.10145 | E9: PL_MODEL row 7
A10: Trading Income | C10: =[1]PL_MODEL!$F$8 -> 219.41796 | D10: =[1]PL_MODEL!$G$8 -> 237.70296 | E10: PL_MODEL row 8
A11: Total Operating Income (Gross Income) | B11: =[1]PL_MODEL!$E$10 -> 3455.9048 | C11: =[1]PL_MODEL!$F$10 -> 5184.6868 | D11: =[1]PL_MODEL!$G$10 -> 5588.8636 | E11: PL_MODEL row 10
A12: Administrative Expenses | C12: =[1]PL_MODEL!$F$16 -> 1896.7498 | D12: =[1]PL_MODEL!$G$16 -> 1953.6523 | E12: PL_MODEL row 16
A13: Impairment on Financial Assets | C13: =[1]PL_MODEL!$F$18 -> 560.10642 | D13: =[1]PL_MODEL!$G$18 -> 579.71014 | E13: PL_MODEL row 18
A14: Profit Before Tax | C14: =[1]PL_MODEL!$F$19 -> 2727.8306 | D14: =[1]PL_MODEL!$G$19 -> 3055.5011 | E14: PL_MODEL row 19
A15: Tax Expense | C15: =[1]PL_MODEL!$F$20 -> 681.95764 | D15: =[1]PL_MODEL!$G$20 -> 763.87528 | E15: PL_MODEL row 20
A16: Net Profit After Tax | C16: =[1]PL_MODEL!$F$21 -> 2045.8729 | D16: =[1]PL_MODEL!$G$21 -> 2291.6258 | E16: PL_MODEL row 21
A18: SECTION B — BALANCE SHEET ITEMS (BALANCE_SHEET, £m)
A19: ITEM | C19: FY2023 | D19: FY2024 | E19: SOURCE ROW
A20: Cash and Central Bank Balances | C20: =[1]BALANCE_SHEET!$F$4 -> 17948.128 | D20: =[1]BALANCE_SHEET!$G$4 -> 19577.952 | E20: BALANCE_SHEET row 4
A21: Loans and Advances to Customers | C21: =[1]BALANCE_SHEET!$F$5 -> 140026.61 | D21: =[1]BALANCE_SHEET!$G$5 -> 144927.54 | E21: BALANCE_SHEET row 5
A22: Investment Securities | C22: =[1]BALANCE_SHEET!$F$6 -> 4200.7982 | D22: =[1]BALANCE_SHEET!$G$6 -> 4347.8261 | E22: BALANCE_SHEET row 6
A23: Other Assets | C23: =[1]BALANCE_SHEET!$F$7 -> 4200.7982 | D23: =[1]BALANCE_SHEET!$G$7 -> 4347.8261 | E23: BALANCE_SHEET row 7
A24: Total On-Balance Sheet Assets | C24: =[1]BALANCE_SHEET!$F$8 -> 166376.33 | D24: =[1]BALANCE_SHEET!$G$8 -> 173201.14 | E24: BALANCE_SHEET row 8
A25: Customer Deposits | C25: =[1]BALANCE_SHEET!$F$10 -> 126023.94 | D25: =[1]BALANCE_SHEET!$G$10 -> 130434.78 | E25: BALANCE_SHEET row 10
A26: Wholesale Funding | C26: =[1]BALANCE_SHEET!$F$11 -> 22684.31 | D26: =[1]BALANCE_SHEET!$G$11 -> 23478.261 | E26: BALANCE_SHEET row 11
A27: Other Liabilities | C27: =[1]BALANCE_SHEET!$F$12 -> 7001.3303 | D27: =[1]BALANCE_SHEET!$G$12 -> 7246.3768 | E27: BALANCE_SHEET row 12
A28: Share Capital | C28: =[1]BALANCE_SHEET!$F$15 -> 8000 | D28: =[1]BALANCE_SHEET!$G$15 -> 8000 | E28: BALANCE_SHEET row 15
A29: Retained Earnings | C29: =[1]BALANCE_SHEET!$F$16 -> 2666.7444 | D29: =[1]BALANCE_SHEET!$G$16 -> 4041.7199 | E29: BALANCE_SHEET row 16

Sheet OWN_FUNDS
A1: CALEDONIA BANK PLC COREP C01 : OWN FUNDS CALCULATION
A2: Regulatory basis: CRR Articles 26-88 | PRA Rulebook: Capital Resources | Reporting period: FY2024
A4: CET1 CAPITAL — COMMON EQUITY TIER 1
A5: ITEM | B5: AMOUNT (£m) | C5: MINIMUM REQUIREMENT | D5: NOTES
A6: Share Capital | B6: =EXTERNAL_INPUTS!D28 -> 8000
A7: Retained Earnings FY2024 | B7: =EXTERNAL_INPUTS!D29 -> 4041.7199
A8: Other Comprehensive Income | B8: 200
A9: Regulatory Deductions | B9: -500
A10: TOTAL CET1 CAPITAL | B10: =SUM(B6:B9) -> 11741.72 | C10: 0.045
A11: AT1 & TIER 1 CAPITAL
A12: AT1 Capital (Additional Tier 1) | B12: 1000
A13: TOTAL TIER 1 CAPITAL | B13: =B10+B12 -> 12741.72 | C13: 0.06
A14: TIER 2 & TOTAL OWN FUNDS
A15: Tier 2 Capital (Subordinated debt) | B15: 2000
A16: TOTAL OWN FUNDS | B16: =B13+B15 -> 14741.72 | C16: 0.08

Sheet CAPITAL_REQUIREMENTS
A1: CALEDONIA BANK PLC — COREP C02 — CAPITAL REQUIREMENTS & RWA
A2: Regulatory basis: CRR Articles 92-386 | Basel III Standardised Approach | Reporting period: FY2024
A4: SECTION A — CREDIT RISK RWA (STANDARDISED APPROACH)
A5: EXPOSURE CLASS | B5: RISK WEIGHT | C5: EXPOSURE (£m) | D5: ALLOCATION (%) | E5: RWA (£m) | F5: BASIS
A6: Retail Mortgages | B6: 0.35 | C6: =EXTERNAL_INPUTS!$D$21*D6 -> 86956.522 | D6: 0.6 | E6: =C6*B6 -> 30434.783 | F6: Basel III Art 125
A7: Corporate Loans | B7: 1 | C7: =EXTERNAL_INPUTS!$D$21*D7 -> 36231.884 | D7: 0.25 | E7: =C7*B7 -> 36231.884 | F7: Basel III Art 122
A8: Consumer Credit | B8: 0.75 | C8: =EXTERNAL_INPUTS!$D$21*D8 -> 21739.13 | D8: 0.15 | E8: =C8*B8 -> 16304.348 | F8: Basel III Art 123
A9: Sovereign (UK Gilts) | B9: 0 | C9: 1000 | E9: =C9*B9 -> 0 | F9: Basel III Art 114
A10: TOTAL CREDIT RWA | C10: =SUM(C6:C9) -> 145927.54 | E10: =SUM(E6:E9) -> 82971.014
A12: SECTION B — OPERATIONAL RISK RWA (BASIC INDICATOR APPROACH)
A13: Gross Income | B13: Value (£m)
A14: Gross Income FY2022 | B14: =EXTERNAL_INPUTS!B11 -> 3455.9048
A15: Gross Income FY2023 | B15: =EXTERNAL_INPUTS!C11 -> 5184.6868
A16: Gross Income FY2024 | B16: =EXTERNAL_INPUTS!D11 -> 5588.8636
A17: 3-Year Average Gross Income | B17: =AVERAGE(B14:B16) -> 4743.1517
A18: OPERATIONAL RISK RWA | B18: =B17*B19 -> 711.47276
A19: BIA Alpha Factor (CRR Art 315) | B19: 0.15
A20: Basic Indicator Approach — Average Gross Income x 15% per CRR Article 315
A22: SECTION C — CAPITAL RATIOS SUMMARY
A23: RATIO | B23: FORMULA | C23: RESULT | D23: MINIMUM | E23: HEADROOM | F23: STATUS
A24: CET1 Ratio | B24: CET1 / Total RWA | C24: =OWN_FUNDS!B10/(CAPITAL_REQUIREMENTS!E10+B18) -> 0.14031275 | D24: 0.045 | E24: =C24-D24 -> 0.09531275 | F24: =IF(C24>=D24,"PASS","FAIL") -> PASS
A25: Tier 1 Ratio | B25: Tier 1 / Total RWA | C25: =OWN_FUNDS!B13/(CAPITAL_REQUIREMENTS!E10+CAPITAL_REQUIREMENTS!B18) -> 0.15226268 | D25: 0.06 | E25: =C25-D25 -> 0.092262682 | F25: =IF(C25>=D25,"PASS","FAIL") -> PASS
A26: Total Capital Ratio | B26: Own Funds / Total RWA | C26: =OWN_FUNDS!B16/(CAPITAL_REQUIREMENTS!E10+CAPITAL_REQUIREMENTS!B18) -> 0.17616254 | D26: 0.08 | E26: =C26-D26 -> 0.096162545 | F26: =IF(C26>=D26,"PASS","FAIL") -> PASS

Sheet LEVERAGE RATIO
A1: CALEDONIA BANK PLC — COREP C47 — UK LEVERAGE RATIO
A2: Regulatory basis: UK Leverage Ratio Framework 2015 | PRA Policy Statement PS21/21 | Reporting period: FY2024
A4: LEVERAGE RATIO CALCULATION
A5: ITEM | B5: VALUE (£m) | C5: NOTES
A6: Tier 1 Capital | B6: =OWN_FUNDS!B13 -> 12741.72 | C6: Linked from OWN_FUNDS sheet
A7: Total On-Balance Sheet Assets | B7: =EXTERNAL_INPUTS!D24 -> 173201.14 | C7: Linked via EXTERNAL_INPUTS
A8: Off-Balance Sheet Commitments | B8: 500 | C8: Hardcoded estimate
A9: Total Exposure Measure | B9: =B7+B8 -> 173701.14 | C9: On BS + Off BS
A10: LEVERAGE RATIO | B10: =B6/B9 -> 0.073354268 | C10: =Tier 1 / Total Exposure
A11: UK Minimum Requirement | B11: 0.035 | C11: UK Leverage Ratio Framework
A12: Headroom above minimum | B12: =B10-B11 -> 0.038354268 | C12: Must be positive
A13: Status | B13: =IF(B10>=B11,"PASS","FAIL") -> PASS | C13: Green if PASS, red if FAIL

Sheet FINREP_PL
A1: CALEDONIA BANK PLC — FINREP F02 — INCOME STATEMENT (REGULATORY FORMAT)
A2: Regulatory basis: EBA ITS on Supervisory Reporting | PRA Supervisory Statement SS34/15 | Reporting period: FY2024
A4: REGULATORY INCOME STATEMENT
A5: FINREP LINE ITEM | B5: FY2024 (£m) | C5: FY2023 (£m) | D5: CHANGE (£m) | E5: CHANGE % | F5: EBA REFERENCE
A6: Interest Income | B6: =EXTERNAL_INPUTS!D6 -> 9864.6135 | C6: =EXTERNAL_INPUTS!C6 -> 8909.6478 | D6: =B6-C6 -> 954.96569 | E6: =D6/ABS(C6) -> 0.10718333 | F6: F02 row 010
A7: Interest Expense | B7: =EXTERNAL_INPUTS!D7 -> 5110.5543 | C7: =EXTERNAL_INPUTS!C7 -> 4521.2886 | D7: =B7-C7 -> 589.26575 | E7: =D7/ABS(C7) -> 0.13033137 | F7: F02 row 020
A8: Net Interest Income | B8: =EXTERNAL_INPUTS!D8 -> 4754.0592 | C8: =EXTERNAL_INPUTS!C8 -> 4388.3592 | D8: =B8-C8 -> 365.69994 | E8: =D8/ABS(C8) -> 0.083334094 | F8: F02 row 030
A9: Fee and Commission Income | B9: =EXTERNAL_INPUTS!D9 -> 597.10145 | C9: =EXTERNAL_INPUTS!C9 -> 576.90961 | D9: =B9-C9 -> 20.191836 | E9: =D9/ABS(C9) -> 0.035 | F9: F02 row 200
A10: Trading Income | B10: =EXTERNAL_INPUTS!D10 -> 237.70296 | C10: =EXTERNAL_INPUTS!C10 -> 219.41796 | D10: =B10-C10 -> 18.284997 | E10: =D10/ABS(C10) -> 0.083334094 | F10: F02 row 090
A11: Administrative Expenses | B11: =EXTERNAL_INPUTS!D12 -> 1953.6523 | C11: =EXTERNAL_INPUTS!C12 -> 1896.7498 | D11: =B11-C11 -> 56.902495 | E11: =D11/ABS(C11) -> 0.03 | F11: F02 row 300
A12: Impairment on Financial Assets | B12: =EXTERNAL_INPUTS!D13 -> 579.71014 | C12: =EXTERNAL_INPUTS!C13 -> 560.10642 | D12: =B12-C12 -> 19.603725 | E12: =D12/ABS(C12) -> 0.035 | F12: F02 row 380
A13: Profit Before Tax | B13: =EXTERNAL_INPUTS!D14 -> 3055.5011 | C13: =EXTERNAL_INPUTS!C14 -> 2727.8306 | D13: =B13-C13 -> 327.67055 | E13: =D13/ABS(C13) -> 0.1201213 | F13: F02 row 420
A14: Tax Expense | B14: =EXTERNAL_INPUTS!D15 -> 763.87528 | C14: =EXTERNAL_INPUTS!C15 -> 681.95764 | D14: =B14-C14 -> 81.917639 | E14: =D14/ABS(C14) -> 0.1201213 | F14: F02 row 430
A15: Net Profit After Tax | B15: =EXTERNAL_INPUTS!D16 -> 2291.6258 | C15: =EXTERNAL_INPUTS!C16 -> 2045.8729 | D15: =B15-C15 -> 245.75292 | E15: =D15/ABS(C15) -> 0.1201213 | F15: F02 row 440

Sheet FINREP_BS
A1: CALEDONIA BANK PLC — FINREP F01 — BALANCE SHEET (REGULATORY FORMAT)
A2: Regulatory basis: EBA ITS on Supervisory Reporting | PRA Supervisory Statement SS34/15 | Reporting period: FY2024
A4: REGULATORY BALANCE SHEET
A5: FINREP LINE ITEM | B5: FY2024 (£m) | C5: FY2023 (£m) | D5: EBA REFERENCE | E5: NOTES
A6: ASSETS
A7: Cash and Central Bank Balances | B7: =EXTERNAL_INPUTS!D20 -> 19577.952 | C7: =EXTERNAL_INPUTS!C20 -> 17948.128 | D7: F01 row 010 | E7: Linked via EXTERNAL_INPUTS
A8: Loans and Advances to Customers | B8: =EXTERNAL_INPUTS!D21 -> 144927.54 | C8: =EXTERNAL_INPUTS!C21 -> 140026.61 | D8: F01 row 050 | E8: Linked via EXTERNAL_INPUTS
A9: Investment Securities | B9: =EXTERNAL_INPUTS!D22 -> 4347.8261 | C9: =EXTERNAL_INPUTS!C22 -> 4200.7982 | D9: F01 row 070 | E9: Linked via EXTERNAL_INPUTS
A10: Other Assets | B10: =EXTERNAL_INPUTS!D23 -> 4347.8261 | C10: =EXTERNAL_INPUTS!C23 -> 4200.7982 | D10: F01 row 300 | E10: Linked via EXTERNAL_INPUTS
A11: TOTAL ASSETS | B11: =SUM(B7:B10) -> 173201.14 | C11: =SUM(C7:C10) -> 166376.33 | D11: F01 row 380 | E11: Must match FPA Balance Sheet
A12: LIABILITIES
A13: Customer Deposits | B13: =EXTERNAL_INPUTS!D25 -> 130434.78 | C13: =EXTERNAL_INPUTS!C25 -> 126023.94 | D13: F01 row 010 | E13: Linked via EXTERNAL_INPUTS
A14: Wholesale Funding | B14: =EXTERNAL_INPUTS!D26 -> 23478.261 | C14: =EXTERNAL_INPUTS!C26 -> 22684.31 | D14: F01 row 050 | E14: Linked via EXTERNAL_INPUTS
A15: Other Liabilities | B15: =EXTERNAL_INPUTS!D27 -> 7246.3768 | C15: =EXTERNAL_INPUTS!C27 -> 7001.3303 | D15: F01 row 100 | E15: Linked via EXTERNAL_INPUTS
A16: TOTAL LIABILITIES | B16: =SUM(B13:B15) -> 161159.42 | C16: =SUM(C13:C15) -> 155709.58 | D16: F01 row 300 | E16: Must match FPA Balance Sheet
A17: EQUITY
A18: Share Capital | B18: =EXTERNAL_INPUTS!D28 -> 8000 | C18: =EXTERNAL_INPUTS!C28 -> 8000 | D18: F01 row 010 | E18: Linked via EXTERNAL_INPUTS
A19: Retained Earnings | B19: =EXTERNAL_INPUTS!D29 -> 4041.7199 | C19: =EXTERNAL_INPUTS!C29 -> 2666.7444 | D19: F01 row 020 | E19: Linked via EXTERNAL_INPUTS
A20: TOTAL EQUITY | B20: =SUM(B18:B19) -> 12041.72 | C20: =SUM(C18:C19) -> 10666.744 | D20: F01 row 300 | E20: Must match FPA Balance Sheet
A21: BALANCE CHECK | B21: =B11-B16-B20 -> 0 | C21: =C11-C16-C20 -> 0

Sheet DATA_QUALITY
A1: CALEDONIA BANK PLC — DATA QUALITY & REGULATORY RECONCILIATION
A2: Purpose: Reconcile FinRep regulatory returns to management accounts | Identify and document any reclassifications
A4: SECTION A — FINREP VS MANAGEMENT ACCOUNTS RECONCILIATION
A6: LINE ITEM | B6: FINREP (£m) | C6: MGMT ACCOUNTS (£m) | D6: DIFFERENCE (£m) | E6: EXPLANATION
A7: Net Interest Income | B7: =FINREP_PL!B8 -> 4754.0592 | C7: =EXTERNAL_INPUTS!D8 -> 4754.0592 | D7: =B7-C7 -> 0 | E7: Should be 0
A8: Total Operating Income | B8: =FINREP_PL!B8+FINREP_PL!B9+FINREP_PL!B10 -> 5588.8636 | C8: =EXTERNAL_INPUTS!D11 -> 5588.8636 | D8: =B8-C8 -> 0 | E8: Should be 0
A9: Administrative Expenses | B9: =FINREP_PL!B11 -> 1953.6523 | C9: =EXTERNAL_INPUTS!D12 -> 1953.6523 | D9: =B9-C9 -> 0 | E9: Should be 0
A10: Loan Loss Provisions | B10: =FINREP_PL!B12 -> 579.71014 | C10: =EXTERNAL_INPUTS!D13 -> 579.71014 | D10: =B10-C10 -> 0 | E10: Should be 0
A11: Net Profit After Tax | B11: =FINREP_PL!B15 -> 2291.6258 | C11: =EXTERNAL_INPUTS!D16 -> 2291.6258 | D11: =B11-C11 -> 0 | E11: Should be 0
A13: Trading Income reclassified within Total Operating Income — FinRep and management accounts now reconcile
A15: SECTION B — PRA SUBMISSION CALENDAR FY2024
A16: RETURN | B16: REPORTING PERIOD | C16: SUBMISSION DEADLINE | D16: STATUS
A17: COREP Q1 2024 | B17: 45382 | C17: 45412 | D17: SUBMITTED
A18: COREP Q2 2024 | B18: 45473 | C18: 45503 | D18: SUBMITTED
A19: COREP Q3 2024 | B19: 45565 | C19: 45595 | D19: SUBMITTED
A20: COREP Q4 2024 | B20: 45657 | C20: 45687 | D20: SUBMITTED
A21: FinRep Annual 2024 | B21: 45657 | C21: 45716 | D21: SUBMITTED
A23: Note: All returns submitted within PRA deadlines. Solo entity submissions due T+30 days. Group consolidated submissions due T+45 days per EBA ITS Article 3.
